cli/__init__.py
cli/main.py
piquant/__init__.py
piquant/data.py
piquant/quant.py
pyqnt/__init__.py
pyqnt/data.py
pyqnt/quant.py
pyqnt-0.0.1.dist-info/LICENSE
pyqnt-0.0.1.dist-info/METADATA
pyqnt-0.0.1.dist-info/WHEEL
pyqnt-0.0.1.dist-info/entry_points.txt
pyqnt-0.0.1.dist-info/top_level.txt
pyqnt-0.0.1.dist-info/RECORD
